validator_collection/__init__.py
validator_collection/_compat.py
validator_collection/_decorators.py
validator_collection/_version.py
validator_collection/checkers.py
validator_collection/errors.py
validator_collection/validators.py
validator_collection-1.3.8.dist-info/LICENSE
validator_collection-1.3.8.dist-info/METADATA
validator_collection-1.3.8.dist-info/WHEEL
validator_collection-1.3.8.dist-info/top_level.txt
validator_collection-1.3.8.dist-info/RECORD
